karrio/mappers/tge/__init__.py
karrio/mappers/tge/mapper.py
karrio/mappers/tge/proxy.py
karrio/mappers/tge/settings.py
karrio/plugins/tge/__init__.py
karrio/providers/tge/__init__.py
karrio/providers/tge/error.py
karrio/providers/tge/manifest.py
karrio/providers/tge/rate.py
karrio/providers/tge/units.py
karrio/providers/tge/utils.py
karrio/providers/tge/shipment/__init__.py
karrio/providers/tge/shipment/create.py
karrio/schemas/tge/__init__.py
karrio/schemas/tge/error_response.py
karrio/schemas/tge/label_request.py
karrio/schemas/tge/label_response.py
karrio/schemas/tge/manifest_request.py
karrio/schemas/tge/manifest_response.py
karrio/schemas/tge/rate_request.py
karrio/schemas/tge/rate_response.py
karrio_tge-2026.1.4.dist-info/METADATA
karrio_tge-2026.1.4.dist-info/WHEEL
karrio_tge-2026.1.4.dist-info/entry_points.txt
karrio_tge-2026.1.4.dist-info/top_level.txt
karrio_tge-2026.1.4.dist-info/RECORD
